simplecountword/__init__.py
simplecountword-0.1.dist-info/LICENCE.TXT
simplecountword-0.1.dist-info/METADATA
simplecountword-0.1.dist-info/WHEEL
simplecountword-0.1.dist-info/top_level.txt
simplecountword-0.1.dist-info/RECORD
