Metadata-Version: 2.1
Name: simplecountword
Version: 0.1
Summary: this is very basic word count
Home-page: UNKNOWN
Author: husna
Author-email: husna.mehwish09@gmail.com
License: UNKNOWN
Platform: UNKNOWN
Classifier: Programming Language :: Python :: 3
Classifier: License :: OSI Approved :: MIT License
Classifier: Operating System :: OS Independent
License-File: LICENCE.TXT
